pyiqvia/__init__.py
pyiqvia/allergens.py
pyiqvia/asthma.py
pyiqvia/client.py
pyiqvia/const.py
pyiqvia/disease.py
pyiqvia/errors.py
pyiqvia/py.typed
pyiqvia-2023.12.0.dist-info/LICENSE
pyiqvia-2023.12.0.dist-info/METADATA
pyiqvia-2023.12.0.dist-info/WHEEL
pyiqvia-2023.12.0.dist-info/RECORD
